aococr/__init__.py
aococr/config.py
aococr/data/fontsize_10x6.txt
aococr/data/fontsize_6x4.txt
aococr/ocr.py
aococr/parsing.py
aococr/resources.py
aococr-1.0.0.dist-info/LICENSE
aococr-1.0.0.dist-info/METADATA
aococr-1.0.0.dist-info/WHEEL
aococr-1.0.0.dist-info/entry_points.txt
aococr-1.0.0.dist-info/RECORD
