Metadata-Version: 2.1
Name: aococr
Version: 1.0.0
Summary: Advent of Code ASCII-art character recognition
Author: bjarkemoensted
Author-email: bjarkemoensted@gmail.com
Requires-Python: >=3.10,<4.0
Classifier: Programming Language :: Python
Classifier: Programming Language :: Python :: 3
Classifier: Programming Language :: Python :: 3.10
Classifier: Programming Language :: Python :: 3.11
Classifier: Programming Language :: Python :: 3.12
